Metadata-Version: 1.0
Name: rock-library
Version: 1.0.0
Summary: A Python library for ETL operations
Home-page: https://github.com/yourusername/my_library
Author: Your Name
Author-email: your.email@example.com
License: UNKNOWN
Platform: UNKNOWN
